setup.py
pyweechat/__init__.py
pyweechat/buffer.py
pyweechat/client.py
pyweechat/exceptions.py
pyweechat/message.py
pyweechat/socket.py
pyweechat.egg-info/PKG-INFO
pyweechat.egg-info/SOURCES.txt
pyweechat.egg-info/dependency_links.txt
pyweechat.egg-info/not-zip-safe
pyweechat.egg-info/top_level.txt