Metadata-Version: 1.1
Name: pyweechat
Version: 0.2
Summary: Python library for communicating with an weechat irc relay
Home-page: http://github.com/k0rmarun/pyweechat
Author: Niels Bernlöhr
Author-email: kormarun@gmail.com
License: MIT
Platform: UNKNOWN
Classifier: Development Status :: 4 - Beta
Classifier: Environment :: Console
Classifier: Intended Audience :: End Users/Desktop
Classifier: Topic :: Communications :: Chat :: Internet Relay Chat
Classifier: Topic :: Utilities
Classifier: License :: OSI Approved :: MIT License
Classifier: Programming Language :: Python :: 3
Classifier: Programming Language :: Python :: 3.3
Classifier: Programming Language :: Python :: 3.4
Classifier: Programming Language :: Python :: 3.5
